judyb
